{"stats":{"minecraft:custom":{"minecraft:interact_with_crafting_table":47,"minecraft:open_barrel":34,"minecraft:leave_game":7,"minecraft:time_since_death":102074,"minecraft:sprint_one_cm":998710,"minecraft:damage_blocked_by_shield":1350,"minecraft:drop":53,"minecraft:talked_to_villager":3,"minecraft:play_time":387962,"minecraft:deaths":11,"minecraft:jump":7797,"minecraft:walk_on_water_one_cm":59790,"minecraft:interact_with_furnace":27,"minecraft:interact_with_loom":7,"minecraft:sleep_in_bed":9,"minecraft:waystone_activated":2,"minecraft:damage_dealt":42685,"minecraft:crouch_one_cm":98593,"minecraft:interact_with_smoker":18,"minecraft:mob_kills":225,"minecraft:damage_dealt_resisted":5592,"minecraft:climb_one_cm":3309,"minecraft:walk_one_cm":884303,"minecraft:damage_dealt_absorbed":30,"minecraft:sneak_time":24696,"minecraft:walk_under_water_one_cm":66377,"minecraft:interact_with_blast_furnace":12,"minecraft:total_world_time":387962,"minecraft:raid_trigger":1,"minecraft:time_since_rest":47498,"minecraft:damage_taken":8162,"minecraft:swim_one_cm":81952,"minecraft:fly_one_cm":1358686,"minecraft:open_chest":101,"minecraft:fall_one_cm":227474},"minecraft:used":{"minecraft:iron_shovel":84,"minecraft:poppy":1,"minecraft:decorated_pot":1,"minecraft:shield":36,"minecraft:carrot":9,"minecraft:allium":3,"born_in_chaos_v1:smoked_flesh":9,"biomeswevegone:tall_white_allium":2,"born_in_chaos_v1:gnawed_bones":1,"minecraft:oak_sapling":15,"minecraft:furnace":5,"minecraft:potato":16,"upgrade_aquatic:mulberry":4,"minecraft:stone_pickaxe":229,"minecraft:oak_planks":106,"minecraft:wooden_pickaxe":43,"biomesoplenty:lavender":5,"minecraft:diamond_axe":98,"minecraft:blast_furnace":1,"iceandfire:silver_pickaxe":209,"born_in_chaos_v1:smoked_monster_flesh":6,"minecraft:diamond_sword":535,"iceandfire:silver_sword":45,"minecraft:torch":18,"minecraft:dirt":84,"farmersdelight:rope":14,"minecraft:iron_hoe":107,"minecraft:diamond_chestplate":1,"alexscaves:spelunkery_table":1,"minecraft:cooked_beef":6,"farmersdelight:tomato_seeds":4,"minecraft:cobbled_deepslate":1,"minecraft:wheat_seeds":31,"farmersdelight:iron_knife":34,"minecraft:water_bucket":42,"minecraft:birch_planks":40,"farmersdelight:onion":2,"minecraft:crafting_table":17,"minecraft:magenta_bed":1,"minecraft:white_bed":1,"minecraft:smoker":2,"minecraft:oak_log":4,"minecraft:diamond_pickaxe":804,"minecraft:stone_axe":43,"minecraft:cobblestone":222,"minecraft:bucket":43,"quark:oak_chest":8,"minecraft:diamond_leggings":1},"minecraft:dropped":{"minecraft:porkchop":2,"minecraft:crafting_table":1,"minecraft:crossbow":1,"minecraft:flint":1,"born_in_chaos_v1:monster_flesh":1,"minecraft:dirt":16,"gravestone:obituary":7,"minecraft:stone_axe":1,"minecraft:cobbled_deepslate":5,"alexscaves:cave_tablet":1,"minecraft:birch_sapling":2,"minecraft:rotten_flesh":5,"born_in_chaos_v1:smoked_flesh":23,"alexscaves:cave_book":1,"minecraft:gunpowder":8,"create:scoria":1,"born_in_chaos_v1:corpse_maggot":4,"iceandfire:bestiary":1,"iceandfire:silver_pickaxe":1,"minecraft:bread":2,"minecraft:feather":1,"minecraft:chainmail_helmet":1,"minecraft:stick":5,"minecraft:rose_bush":4,"minecraft:paper":1,"minecraft:string":1,"iceandfire:silver_nugget":4,"irons_spellbooks:copper_spell_book":1,"minecraft:raw_iron":27,"alexscaves:cave_codex":1,"minecraft:potato":1,"minecraft:diamond_pickaxe":1,"iceandfire:silver_ingot":4,"minecraft:oak_sapling":26,"minecraft:stone_pickaxe":1,"minecraft:wooden_pickaxe":2},"minecraft:mined":{"minecraft:large_amethyst_bud":1,"create:deepslate_zinc_ore":16,"iceandfire:copper_pile":4,"minecraft:cherry_log":5,"biomeswevegone:lush_grass_block":4,"minecraft:obsidian":5,"minecraft:grass_block":63,"minecraft:spawner":1,"minecraft:magma_block":1,"minecraft:iron_ore":102,"minecraft:cobbled_deepslate":1,"minecraft:fire":5,"minecraft:deepslate_lapis_ore":6,"iceandfire:gold_pile":6,"minecraft:iron_bars":2,"biomesoplenty:webbing":3,"minecraft:deepslate_redstone_ore":6,"minecraft:blackstone":1,"minecraft:smoker":1,"minecraft:torch":6,"minecraft:blast_furnace":1,"create:scoria":1,"born_in_chaos_v1:cobweb_cover":1,"minecraft:cobblestone":34,"minecraft:oak_planks":19,"biomeswevegone:allium_flower_bush":4,"minecraft:wall_torch":5,"minecraft:pink_petals":1,"minecraft:wheat":4,"minecraft:magenta_bed":1,"biomeswevegone:tall_allium":4,"minecraft:grass":99,"minecraft:oak_log":18,"biomeswevegone:ripe_orchard_leaves":2,"minecraft:dirt":49,"minecraft:smooth_basalt":2,"minecraft:oak_leaves":10,"minecraft:deepslate":45,"create:zinc_ore":50,"alexscaves:spelunkery_table":1,"minecraft:diamond_ore":1,"minecraft:tuff":1,"iceandfire:silver_ore":40,"minecraft:deepslate_diamond_ore":46,"farmersdelight:wild_carrots":16,"born_in_chaos_v1:infected_diamond_ore":4,"gravestone:gravestone":10,"minecraft:decorated_pot":1,"born_in_chaos_v1:black_argillite":1,"minecraft:hay_block":2,"farmersdelight:wild_onions":12,"minecraft:redstone_ore":3,"minecraft:furnace":4,"minecraft:andesite":45,"treechop:chopped_log":10,"minecraft:bookshelf":9,"farmersdelight:rope":2,"minecraft:deepslate_iron_ore":37,"minecraft:stone":480,"quark:oak_chest":1,"minecraft:crafting_table":12,"minecraft:emerald_ore":1,"biomeswevegone:tall_pink_allium":11,"minecraft:rose_bush":1,"minecraft:tall_grass":5,"minecraft:copper_ore":6,"biomeswevegone:apple_fruit":5,"minecraft:deepslate_coal_ore":1,"minecraft:lapis_ore":2,"minecraft:deepslate_gold_ore":3,"minecraft:birch_planks":4,"biomeswevegone:tall_white_allium":2,"minecraft:coal_ore":235,"iceandfire:silver_pile":8,"minecraft:gravel":14,"minecraft:dripstone_block":10,"biomesoplenty:stringy_cobweb":1,"minecraft:cobweb":22,"minecraft:gold_ore":3,"minecraft:fern":7},"minecraft:killed":{"born_in_chaos_v1:zombie_clown":1,"minecraft:cave_spider":7,"born_in_chaos_v1:restless_spirit":2,"born_in_chaos_v1:seared_spirit":1,"born_in_chaos_v1:skeleton_demoman":1,"minecraft:spider":13,"born_in_chaos_v1:siamese_skeletonsright":4,"born_in_chaos_v1:scarlet_persecutor":4,"quark:forgotten":1,"minecraft:skeleton":17,"minecraft:chicken":2,"born_in_chaos_v1:skeleton_thrasher":2,"artifacts:mimic":1,"minecraft:pig":3,"minecraft:zombie_villager":2,"born_in_chaos_v1:diamond_termite":5,"minecraft:iron_golem":1,"minecraft:creeper":3,"minecraft:sheep":1,"minecraft:pillager":2,"minecraft:zombie":47,"born_in_chaos_v1:dread_hound":7,"born_in_chaos_v1:corpse_fly":9,"born_in_chaos_v1:door_knight":1,"minecraft:cow":7,"born_in_chaos_v1:siamese_skeletonsleft":4,"alexsmobs:raccoon":1,"born_in_chaos_v1:zombie_bruiser":2,"born_in_chaos_v1:maggot":15,"born_in_chaos_v1:baby_spider":12,"minecraft:horse":3,"minecraft:drowned":1,"born_in_chaos_v1:siamese_skeletons":1,"born_in_chaos_v1:spiritof_chaos":1,"born_in_chaos_v1:fallen_chaos_knight":1,"born_in_chaos_v1:baby_skeleton":4,"born_in_chaos_v1:swarmer":1,"born_in_chaos_v1:mother_spider":1,"born_in_chaos_v1:decrepit_skeleton":17,"born_in_chaos_v1:decaying_zombie":6,"iceandfire:ghost":1,"born_in_chaos_v1:dark_vortex":2,"born_in_chaos_v1:nightmare_stalker":1},"minecraft:picked_up":{"minecraft:wheat":111,"alexscaves:cave_tablet":8,"born_in_chaos_v1:black_argillite":1,"minecraft:string":64,"minecraft:raw_copper":16,"minecraft:gold_nugget":36,"minecraft:cobbled_deepslate":41,"minecraft:bucket":2,"minecraft:rose_bush":8,"born_in_chaos_v1:stimulating_decoction":1,"upgrade_aquatic:mulberry":3,"minecraft:furnace":4,"minecraft:stick":43,"born_in_chaos_v1:shattered_skull":4,"minecraft:torch":11,"minecraft:porkchop":8,"minecraft:cherry_log":5,"iceandfire:rotten_egg":1,"minecraft:pointed_dripstone":5,"born_in_chaos_v1:nightmare_claw":1,"born_in_chaos_v1:damned_demomans_hat_helmet":1,"minecraft:rotten_flesh":88,"create:scoria":1,"farmersdelight:onion":11,"farmersdelight:rope":2,"minecraft:obsidian":4,"irons_spellbooks:copper_spell_book":1,"minecraft:cobblestone":545,"biomesoplenty:lavender":5,"minecraft:birch_log":14,"minecraft:pink_petals":1,"minecraft:magma_block":1,"biomeswevegone:lush_dirt":4,"minecraft:feather":1,"minecraft:cherry_planks":11,"minecraft:andesite":57,"minecraft:smoker":1,"minecraft:potato":2,"alexscaves:cave_book":1,"minecraft:flint":1,"minecraft:tuff":1,"create:raw_zinc":66,"artifacts:flame_pendant":2,"biomeswevegone:shelf_fungi":2,"minecraft:magenta_bed":1,"minecraft:lapis_lazuli":44,"minecraft:dirt":158,"born_in_chaos_v1:monster_skin":6,"minecraft:bone":50,"minecraft:bow":1,"minecraft:wheat_seeds":245,"minecraft:raw_gold":11,"minecraft:oak_planks":17,"born_in_chaos_v1:fire_dust":3,"minecraft:diamond":47,"minecraft:crossbow":2,"minecraft:bread":1,"minecraft:emerald":1,"minecraft:chainmail_helmet":1,"minecraft:oak_sapling":96,"iceandfire:silver_nugget":26,"iceandfire:raw_silver":40,"minecraft:diamond_pickaxe":1,"minecraft:allium":25,"minecraft:crafting_table":15,"minecraft:charcoal":3,"born_in_chaos_v1:diamond_termite_shard":5,"minecraft:chicken":2,"born_in_chaos_v1:seedof_chaos":2,"minecraft:wooden_pickaxe":3,"minecraft:chain":1,"gravestone:obituary":1,"biomeswevegone:tall_white_allium":4,"minecraft:moss_carpet":9,"born_in_chaos_v1:intoxicating_decoction":2,"minecraft:beef":14,"farmersdelight:straw":6,"born_in_chaos_v1:gnawed_bones":1,"minecraft:poppy":1,"minecraft:birch_sapling":4,"minecraft:egg":1,"minecraft:raw_iron":165,"biomeswevegone:tall_allium":6,"born_in_chaos_v1:pieceofdarkmetal":24,"minecraft:carrot":16,"minecraft:redstone":40,"iceandfire:silver_ingot":2,"minecraft:arrow":21,"minecraft:decorated_pot":1,"minecraft:hay_block":2,"alexscaves:spelunkery_table":1,"minecraft:glow_berries":3,"minecraft:mutton":1,"minecraft:bone_block":15,"minecraft:white_wool":1,"born_in_chaos_v1:fused_bone":9,"born_in_chaos_v1:corpse_maggot":24,"biomeswevegone:allium_flower_bush":4,"born_in_chaos_v1:monster_flesh":12,"minecraft:leather":12,"minecraft:birch_planks":4,"biomeswevegone:tall_pink_allium":11,"minecraft:oak_log":249,"minecraft:gunpowder":3,"minecraft:paper":1,"minecraft:white_banner":1,"born_in_chaos_v1:spider_mandible":2,"minecraft:apple":12,"minecraft:rabbit_hide":4,"biomeswevegone:white_allium_flower_bush":1,"minecraft:iron_ingot":4,"born_in_chaos_v1:smoked_flesh":23,"minecraft:book":27,"iceandfire:copper_nugget":28,"minecraft:smooth_basalt":1,"born_in_chaos_v1:ethereal_spirit":7,"minecraft:dandelion":1,"minecraft:dripstone_block":7,"minecraft:gravel":14,"born_in_chaos_v1:dark_rod":4,"minecraft:blast_furnace":1,"quark:oak_chest":1,"minecraft:spider_eye":6,"iceandfire:silver_pickaxe":1,"minecraft:slime_ball":1,"minecraft:coal":409},"minecraft:killed_by":{"born_in_chaos_v1:nightmare_stalker":1,"born_in_chaos_v1:zombie_bruiser":1,"born_in_chaos_v1:phantom_creeper_copy":1,"creeperoverhaul:cave_creeper":1,"alexsmobs:tiger":1,"born_in_chaos_v1:door_knight":2,"born_in_chaos_v1:maggot":1},"minecraft:crafted":{"minecraft:oak_planks":224,"farmersdelight:rope":12,"minecraft:diamond_helmet":1,"minecraft:diamond_leggings":1,"minecraft:smoker":1,"sophisticatedbackpacks:backpack":1,"minecraft:cooked_porkchop":3,"minecraft:crafting_table":7,"farmersdelight:iron_knife":1,"minecraft:wooden_pickaxe":4,"minecraft:birch_planks":40,"minecraft:diamond_pickaxe":1,"minecraft:shield":1,"minecraft:stick":24,"quark:oak_chest":8,"born_in_chaos_v1:smoked_flesh":42,"minecraft:iron_ingot":89,"iceandfire:silver_sword":1,"minecraft:cherry_planks":20,"minecraft:furnace":3,"born_in_chaos_v1:smoked_monster_flesh":10,"alexscaves:cave_map":1,"minecraft:iron_hoe":1,"minecraft:stone_pickaxe":3,"minecraft:diamond_boots":1,"minecraft:wheat":18,"sophisticatedbackpacks:iron_backpack":1,"minecraft:cooked_beef":14,"minecraft:diamond_sword":1,"iceandfire:silver_ingot":12,"minecraft:bucket":1,"minecraft:stone_axe":1,"minecraft:bread":43,"minecraft:air":0,"minecraft:torch":20,"iceandfire:silver_pickaxe":2,"minecraft:diamond_chestplate":1}},"DataVersion":3465}